argvalidate
