Metadata-Version: 1.0
Name: argvalidate
Version: 0.9.0
Summary: Simple argument validator library
Home-page: http://bitbucket.org/sp/python-argvalidate
Author: Stephan Peijnik
Author-email: stephan@peijnik.at
License: LGPLv3+
Platform: UNKNOWN
Classifier: Development Status :: 4 - Beta
Classifier: Intended Audience :: Developers
Classifier: License :: OSI Approved :: GNU Library or Lesser General Public License (LGPL)
Classifier: Operating System :: OS Independent
Classifier: Programming Language :: Python :: 2
Classifier: Topic :: Utilities
